MANIFEST.in
README.rst
helga_urban_jeopardy.py
setup.py
helga_urban_jeopardy.egg-info/PKG-INFO
helga_urban_jeopardy.egg-info/SOURCES.txt
helga_urban_jeopardy.egg-info/dependency_links.txt
helga_urban_jeopardy.egg-info/entry_points.txt
helga_urban_jeopardy.egg-info/requires.txt
helga_urban_jeopardy.egg-info/top_level.txt
helga_urban_jeopardy.egg-info/zip-safe