Metadata-Version: 1.1
Name: helga-urban-jeopardy
Version: 0.1.0
Summary: HALP
Home-page: UNKNOWN
Author: bigjust
Author-email: bigjust@lambdaphil.es
License: LICENSE
Keywords: irc bot urban-jeopardy
Platform: UNKNOWN
Classifier: Development Status :: 1 - Planning
Classifier: License :: OSI Approved :: GNU General Public License v3 (GPLv3)
Classifier: Operating System :: OS Independent
Classifier: Programming Language :: Python
Classifier: Topic :: Software Development :: Libraries :: Python Modules
